odoo/addons/l10n_es_atc/README.rst
odoo/addons/l10n_es_atc/__init__.py
odoo/addons/l10n_es_atc/__manifest__.py
odoo/addons/l10n_es_atc/data/atc_partner.xml
odoo/addons/l10n_es_atc/data/config_parameter_data.xml
odoo/addons/l10n_es_atc/i18n/es.po
odoo/addons/l10n_es_atc/i18n/l10n_es_atc.pot
odoo/addons/l10n_es_atc/models/__init__.py
odoo/addons/l10n_es_atc/models/l10n_es_atc_report.py
odoo/addons/l10n_es_atc/models/res_company.py
odoo/addons/l10n_es_atc/readme/CONFIGURE.md
odoo/addons/l10n_es_atc/readme/CONTRIBUTORS.md
odoo/addons/l10n_es_atc/readme/DESCRIPTION.md
odoo/addons/l10n_es_atc/security/atc_security.xml
odoo/addons/l10n_es_atc/static/description/icon.png
odoo/addons/l10n_es_atc/static/description/index.html
odoo/addons/l10n_es_atc/views/atc_menuitem.xml
odoo/addons/l10n_es_atc/views/res_company_views.xml
odoo_addon_l10n_es_atc-18.0.1.1.1.1.dist-info/METADATA
odoo_addon_l10n_es_atc-18.0.1.1.1.1.dist-info/WHEEL
odoo_addon_l10n_es_atc-18.0.1.1.1.1.dist-info/top_level.txt
odoo_addon_l10n_es_atc-18.0.1.1.1.1.dist-info/RECORD
