Metadata-Version: 2.1
Name: odoo-addon-l10n_es_atc
Version: 18.0.1.1.1.1
Requires-Python: >=3.10
Requires-Dist: odoo-addon-l10n_es_aeat==18.0.*
Requires-Dist: odoo==18.0.*
Summary: =?utf-8?q?Modulo_=27glue=27_de_la_AEAT_para_el_men=C3=BA_de_la_ATC?=
Home-page: https://github.com/OCA/l10n-spain
License: AGPL-3
Author: Binhex System Solutions,Odoo Community Association (OCA)
Author-email: support@odoo-community.org
Classifier: Programming Language :: Python
Classifier: Framework :: Odoo
Classifier: Framework :: Odoo :: 18.0
Classifier: License :: OSI Approved :: GNU Affero General Public License v3
